arglog.py
arglog-2017.6.2.dist-info/LICENSE
arglog-2017.6.2.dist-info/WHEEL
arglog-2017.6.2.dist-info/METADATA
arglog-2017.6.2.dist-info/RECORD
